dclua/__init__.py
dclua/dclua.py
dclua-2.0.dist-info/LICENSE
dclua-2.0.dist-info/METADATA
dclua-2.0.dist-info/WHEEL
dclua-2.0.dist-info/top_level.txt
dclua-2.0.dist-info/RECORD
