Metadata-Version: 2.1
Name: dclua
Version: 2.0
Summary: Library for word declensions
Home-page: https://github.com/syntpump/declensor
Author: Syntpump
Author-email: lynnporu@gmail.com
License: MIT License
Project-URL: Syntpump on GitHub, https://github.com/syntpump
Keywords: nlp
Platform: UNKNOWN
Classifier: Development Status :: 5 - Production/Stable
Classifier: Intended Audience :: Developers
Classifier: Intended Audience :: Science/Research
Classifier: License :: OSI Approved :: MIT License
Requires-Python: >3
